<annotation>
	<folder>Mask</folder>
	<filename>1195.jpg</filename>
	<path>/home/ishani/Desktop/Github/1Datasets/face mask/Train/Mask/1195.jpg</path>
	<source>
		<database>Unknown</database>
	</source>
	<size>
		<width>4231</width>
		<height>2282</height>
		<depth>3</depth>
	</size>
	<segmented>0</segmented>
	<object>
		<name>mask</name>
		<pose>Unspecified</pose>
		<truncated>0</truncated>
		<difficult>0</difficult>
		<bndbox>
			<xmin>1331</xmin>
			<ymin>1068</ymin>
			<xmax>2598</xmax>
			<ymax>2212</ymax>
		</bndbox>
	</object>
</annotation>
